swarmnet/__init__.py
swarmnet/broadcaster.py
swarmnet/logger.py
swarmnet/msg_parser.py
swarmnet/receiver.py
swarmnet/sender.py
swarmnet/swarmnet.py
swarmnet-0.0.8.dist-info/LICENSE
swarmnet-0.0.8.dist-info/METADATA
swarmnet-0.0.8.dist-info/WHEEL
swarmnet-0.0.8.dist-info/top_level.txt
swarmnet-0.0.8.dist-info/RECORD
