Metadata-Version: 2.1
Name: swarmnet
Version: 0.0.8
Summary: A gossip-based swarm communication library
Home-page: https://github.com/tgodfrey0/SwarmNet
Author: Toby Godfrey
Author-email: swarmnet@tgodfrey.com
Classifier: Programming Language :: Python :: 3
Classifier: License :: OSI Approved :: GNU General Public License v3 (GPLv3)
Classifier: Operating System :: OS Independent
Requires-Python: >=3.10
License-File: LICENSE
